CHANGES.txt
README
setup.cfg
setup.py
./emailthis/__init__.py
./emailthis/forms.py
./emailthis/models.py
./emailthis/urls.py
./emailthis/util.py
./emailthis/views.py
django_emailthis.egg-info/PKG-INFO
django_emailthis.egg-info/SOURCES.txt
django_emailthis.egg-info/dependency_links.txt
django_emailthis.egg-info/top_level.txt
emailthis/__init__.py
emailthis/forms.py
emailthis/models.py
emailthis/urls.py
emailthis/util.py
emailthis/views.py