Metadata-Version: 1.0
Name: django-emailthis
Version: 0.2.1-r21
Summary: 
